mypypidemo/__init__.py
mypypidemo/math_utils.py
mypypidemo-0.1.0.dist-info/LICENSE.txt
mypypidemo-0.1.0.dist-info/METADATA
mypypidemo-0.1.0.dist-info/WHEEL
mypypidemo-0.1.0.dist-info/top_level.txt
mypypidemo-0.1.0.dist-info/RECORD
